Metadata-Version: 1.0
Name: mk-distributions
Version: 0.2
Summary: Gaussian and Bionomial distributions by MK
Home-page: UNKNOWN
Author: UNKNOWN
Author-email: UNKNOWN
License: UNKNOWN
Platform: UNKNOWN
